sunnyday_IZPy/__init__.py
sunnyday_IZPy/sunnyday.py
sunnyday_IZPy-2.1.0.dist-info/METADATA
sunnyday_IZPy-2.1.0.dist-info/WHEEL
sunnyday_IZPy-2.1.0.dist-info/top_level.txt
sunnyday_IZPy-2.1.0.dist-info/RECORD
